pypkg/__init__.py
pypkg/__version__.py
pypkg/cli.py
pypkg/config.py
pypkg/main.py
pypkg/tree.py
pypkg/tpl_pkg/.env-tpl
pypkg/tpl_pkg/.gitignore-tpl
pypkg/tpl_pkg/LICENSE-tpl
pypkg/tpl_pkg/README.md-tpl
pypkg/tpl_pkg/__init__.py
pypkg/tpl_pkg/publish.sh-tpl
pypkg/tpl_pkg/pyproject.toml-tpl
pypkg/tpl_pkg/${app_name}/__init__.py
pypkg/tpl_pkg/${app_name}/__init__.py-tpl
pypkg/tpl_pkg/${app_name}/__version__.py-tpl
pypkg/tpl_pkg/${app_name}/cli.py-tpl
pypkg/tpl_pkg/${app_name}/config.py-tpl
pypkg/tpl_pkg/${app_name}/main.py-tpl
pypkg_tpl-2024.9.21.dist-info/METADATA
pypkg_tpl-2024.9.21.dist-info/WHEEL
pypkg_tpl-2024.9.21.dist-info/entry_points.txt
pypkg_tpl-2024.9.21.dist-info/licenses/LICENSE
pypkg_tpl-2024.9.21.dist-info/RECORD
