Metadata-Version: 2.1
Name: pypkg-tpl
Version: 2024.9.21
Author-email: mikigo <huangmingqiang@uniontech.com>
License: GPL2.0
License-File: LICENSE
Requires-Python: >=3.7
Requires-Dist: click
